polyaxon_cli/__init__.py
polyaxon_cli/exceptions.py
polyaxon_cli/logger.py
polyaxon_cli/main.py
polyaxon_cli/pkg.py
polyaxon_cli/cli/__init__.py
polyaxon_cli/cli/admin.py
polyaxon_cli/cli/auth.py
polyaxon_cli/cli/bookmark.py
polyaxon_cli/cli/build.py
polyaxon_cli/cli/check.py
polyaxon_cli/cli/cluster.py
polyaxon_cli/cli/completion.py
polyaxon_cli/cli/config.py
polyaxon_cli/cli/dashboard.py
polyaxon_cli/cli/deploy.py
polyaxon_cli/cli/experiment.py
polyaxon_cli/cli/experiment_group.py
polyaxon_cli/cli/init.py
polyaxon_cli/cli/job.py
polyaxon_cli/cli/notebook.py
polyaxon_cli/cli/project.py
polyaxon_cli/cli/run.py
polyaxon_cli/cli/superuser.py
polyaxon_cli/cli/tensorboard.py
polyaxon_cli/cli/upload.py
polyaxon_cli/cli/user.py
polyaxon_cli/cli/version.py
polyaxon_cli/cli/getters/__init__.py
polyaxon_cli/cli/getters/build.py
polyaxon_cli/cli/getters/experiment.py
polyaxon_cli/cli/getters/experiment_group.py
polyaxon_cli/cli/getters/job.py
polyaxon_cli/cli/getters/project.py
polyaxon_cli/cli/getters/user.py
polyaxon_cli/client/__init__.py
polyaxon_cli/client/client.py
polyaxon_cli/client/exceptions.py
polyaxon_cli/client/tracking.py
polyaxon_cli/managers/__init__.py
polyaxon_cli/managers/auth.py
polyaxon_cli/managers/base.py
polyaxon_cli/managers/build_job.py
polyaxon_cli/managers/cli.py
polyaxon_cli/managers/compose.py
polyaxon_cli/managers/config.py
polyaxon_cli/managers/deploy.py
polyaxon_cli/managers/experiment.py
polyaxon_cli/managers/experiment_group.py
polyaxon_cli/managers/experiment_job.py
polyaxon_cli/managers/ignore.py
polyaxon_cli/managers/job.py
polyaxon_cli/managers/project.py
polyaxon_cli/run/__init__.py
polyaxon_cli/run/conda.py
polyaxon_cli/run/docker.py
polyaxon_cli/run/params.py
polyaxon_cli/run/platform.py
polyaxon_cli/schemas/__init__.py
polyaxon_cli/schemas/cli_configuration.py
polyaxon_cli/schemas/global_configuration.py
polyaxon_cli/utils/__init__.py
polyaxon_cli/utils/cache.py
polyaxon_cli/utils/constants.py
polyaxon_cli/utils/files.py
polyaxon_cli-0.6.1.dist-info/LICENSE
polyaxon_cli-0.6.1.dist-info/METADATA
polyaxon_cli-0.6.1.dist-info/WHEEL
polyaxon_cli-0.6.1.dist-info/entry_points.txt
polyaxon_cli-0.6.1.dist-info/top_level.txt
polyaxon_cli-0.6.1.dist-info/RECORD
