Metadata-Version: 2.1
Name: polyaxon-cli
Version: 0.6.1
Summary: Command Line Interface (CLI) for Polyaxon.
Home-page: https://github.com/polyaxon/polyaxon-cli
Author: Mourad Mourafiq
Author-email: mourad@polyaxon.com
Maintainer: Mourad Mourafiq
Maintainer-email: mourad@polyaxon.com
License: MIT
Keywords: polyaxon,tensorFlow,deep-learning,machine-learning,data-science,neural-networks,artificial-intelligence,ai,reinforcement-learning,kubernetes
Platform: any
Classifier: Programming Language :: Python
Classifier: Programming Language :: Python :: 2
Classifier: Programming Language :: Python :: 2.7
Classifier: Programming Language :: Python :: 3
Classifier: Programming Language :: Python :: 3.5
Classifier: Programming Language :: Python :: 3.6
Classifier: Programming Language :: Python :: 3.7
Classifier: Operating System :: OS Independent
Classifier: Intended Audience :: Developers
Classifier: Intended Audience :: Science/Research
Classifier: Topic :: Scientific/Engineering :: Artificial Intelligence
Requires-Python: >=2.7, !=3.0.*, !=3.1.*, !=3.2.*, !=3.3.*, !=3.4.*
Requires-Dist: click (==7.0)
Requires-Dist: click-completion (==0.5.1)
Requires-Dist: pathlib (==1.0.1)
Requires-Dist: polyaxon-client (==0.6.1)
Requires-Dist: polyaxon-deploy (==0.6.1)
Requires-Dist: polyaxon-dockerizer (==0.1.0)
Requires-Dist: raven (==6.7.0)
Requires-Dist: tabulate (==0.8.2)
